scrape/__init__.py
scrape/scrape.py
scrape_md-1.0.0.dist-info/METADATA
scrape_md-1.0.0.dist-info/WHEEL
scrape_md-1.0.0.dist-info/entry_points.txt
scrape_md-1.0.0.dist-info/top_level.txt
scrape_md-1.0.0.dist-info/RECORD
