Metadata-Version: 2.1
Name: scrape_md
Version: 1.0.0
Summary: Scrape.md is a command line interface for scraping and converting website content to Markdown.
Home-page: https://github.com/bobbyhiddn/Scrape.md
Author: Micah Longmire
Author-email: mlmicahlongmire@gmail.com
Classifier: Programming Language :: Python :: 3
Classifier: License :: OSI Approved :: MIT License
Classifier: Operating System :: OS Independent
Requires-Python: >=3.6
Requires-Dist: requests
Requires-Dist: beautifulsoup4
Requires-Dist: openai
Requires-Dist: click
